streaminguploadserver/__init__.py
streaminguploadserver/__main__.py
streaminguploadserver-0.0.3.dist-info/LICENSE
streaminguploadserver-0.0.3.dist-info/METADATA
streaminguploadserver-0.0.3.dist-info/WHEEL
streaminguploadserver-0.0.3.dist-info/top_level.txt
streaminguploadserver-0.0.3.dist-info/RECORD
