Metadata-Version: 2.1
Name: streaminguploadserver
Version: 0.0.3
Summary: Streaming upload server in Python extended from http.server
Home-page: https://github.com/NteRySin/streaminguploadserver
Author: NteRySin
Author-email: author@example.com
Project-URL: Bug Tracker, https://github.com/NteRySin/streaminguploadserver/issues
Classifier: Programming Language :: Python :: 3
Classifier: License :: OSI Approved :: MIT License
Classifier: Operating System :: OS Independent
Requires-Python: >=3.6
License-File: LICENSE
Requires-Dist: multipart <0.3,>=0.2
Requires-Dist: uploadserver <6,>=5.0.0
